README.md
setup.py
fib_py/__init__.py
fib_py/version.py
fib_py/cmd/__init__.py
fib_py/cmd/fib_numb.py
fib_py/fib_calc/__init__.py
fib_py/fib_calc/fib_number.py
fib_py/fib_calc/fib_numbers.py
ssshikari_fib_py.egg-info/PKG-INFO
ssshikari_fib_py.egg-info/SOURCES.txt
ssshikari_fib_py.egg-info/dependency_links.txt
ssshikari_fib_py.egg-info/entry_points.txt
ssshikari_fib_py.egg-info/requires.txt
ssshikari_fib_py.egg-info/top_level.txt
tests/fib_py/__init__.py
tests/fib_py/fib_calc/__init__.py
tests/fib_py/fib_calc/test_fib_number.py
tests/fib_py/fib_calc/test_fib_numbers.py