Metadata-Version: 2.1
Name: ssshikari-fib-py
Version: 0.0.2
Summary: Calculates a Fibonacci number
Home-page: https://github.com/ValikMinak/fib
Author: ssshikari
Author-email: ssshikari@gmail.com
License: UNKNOWN
Platform: UNKNOWN
Classifier: Development Status :: 4 - Beta
Classifier: Programming Language :: Python :: 3
Classifier: Operating System :: OS Independent
Requires-Python: >=3
